conmo/__init__.py
conmo/conf.py
conmo/experiment.py
conmo/algorithms/__init__.py
conmo/algorithms/algorithm.py
conmo/algorithms/cnn_1d.py
conmo/algorithms/keras_autoencoder.py
conmo/algorithms/multilayer_perceptron.py
conmo/algorithms/one_class_svm.py
conmo/algorithms/pca_mahalanobis.py
conmo/algorithms/random_forest.py
conmo/algorithms/tests/__init__.py
conmo/algorithms/tests/conftest.py
conmo/algorithms/tests/test_keras_autoencoder.py
conmo/algorithms/tests/test_one_class_svm.py
conmo/algorithms/tests/test_pca_mahalanobis.py
conmo/analytics/__init__.py
conmo/analytics/analytic.py
conmo/datasets/__init__.py
conmo/datasets/batteries_degradation.py
conmo/datasets/dataset.py
conmo/datasets/mars_science_laboratory_mission.py
conmo/datasets/nasa_turbofan_degradation.py
conmo/datasets/server_machine_dataset.py
conmo/datasets/soil_moisture_active_passive_satellite.py
conmo/metrics/__init__.py
conmo/metrics/accuracy.py
conmo/metrics/metric.py
conmo/metrics/rmspe.py
conmo/metrics/tests/__init__.py
conmo/metrics/tests/conftest.py
conmo/metrics/tests/test_accuracy.py
conmo/preprocesses/__init__.py
conmo/preprocesses/binarizer.py
conmo/preprocesses/custom.py
conmo/preprocesses/preprocess.py
conmo/preprocesses/rul_imputation.py
conmo/preprocesses/savitzky_golay_filter.py
conmo/preprocesses/sequence_windowing.py
conmo/preprocesses/simple_exponential_smoothing.py
conmo/preprocesses/sklearn_preprocess.py
conmo/splitters/__init__.py
conmo/splitters/sklearn_splitter.py
conmo/splitters/splitter.py
conmo-1.0.1.dist-info/METADATA
conmo-1.0.1.dist-info/WHEEL
conmo-1.0.1.dist-info/top_level.txt
conmo-1.0.1.dist-info/RECORD
